{
  "whatsapp": "5492916443282",
  "apartments": {
    "ohiggins": {
      "price": 80,
      "booking": "https://www.booking.com/hotel/ar/ohiggins-bahia-premium.es.html?aid=318615&label=Spanish_Argentina_ES_AR_20153587225-6h15TH8LvM25bNckrW9zZwS217247257083%3Apl%3Ata%3Ap1%3Ap2%3Aac%3Aap%3Aneg%3Afi%3Atidsa-162435869305%3Alp1000024%3Ali%3Adec%3Adm&sid=4769bbc44e5dd6685914b9365180ad59&dest_id=-977594&dest_type=city&dist=0&group_adults=2&group_children=0&hapos=1&hpos=1&no_rooms=1&req_adults=2&req_children=0&room1=A%2CA&sb_price_type=total&sr_order=popularity&srepoch=1783479474&srpvid=af82146cebcd023f&type=total&ucfs=1&",
      "airbnb": "https://es-l.airbnb.com/rooms/1195610537617927699?guests=1&adults=1&s=67&unique_share_id=5b536c52-a039-435f-976f-f39a051dbf79",
      "instagram": "https://instagram.com/ohigginsbahiapremium",
      "facebook": "https://facebook.com/ohigginsbahiapremium",
      "email": "ohigginsbahiapremium@gmail.com.ar"
    },
    "santafe": {
      "price": 185,
      "booking": "https://www.booking.com/hotel/ar/sfe-bahia-premium-sky-and-sea.es.html?label=gen173rf-10CAEoggI46AdIM1gDaAyIAQGYATO4ARfIAQzYAQPoAQH4AQGIAgGiAhBiYWhpYXByZW1pdW0uY29tqAIBuALZ_LbSBsACAdICJDJiMDViNmNmLTU5NGEtNDg5ZS05ZGI0LWIxZWJhMDk3MWQ3Y9gCAeACAQ&aid=304142&ucfs=1&arphpl=1&checkin=2026-07-08&checkout=2026-07-09&adplat=www-homescreen-recently_viewed_carousel-stays-n_a-n_a",
      "airbnb": "https://www.airbnb.com.ar/rooms/1668440721821411584?check_in=2026-07-15&check_out=2026-07-16&guests=1&adults=1&s=67&unique_share_id=3d890202-2b96-4093-b413-453a8715d992",
      "instagram": "https://instagram.com/sfebahiapremium",
      "facebook": "https://facebook.com/sfebahiapremium",
      "email": "sfebahiapremium@gmail.com.ar"
    }
  }
}